{
  "name": "~TODO~",
  "description": "A Marcelle Application",
  "version": "0.0.0",
  "keywords": ["marcelle"],
  "main": "public/bundle.js",
  "type": "module",
  "scripts": {
    "dev": "vite",
    "build": "vite build"
  },
  "dependencies": {
    "@marcellejs/core": "workspace:*"
  },
  "devDependencies": {
    "@marcellejs/design-system": "workspace:*",
    "@marcellejs/devtools": "workspace:*",
    "@sveltejs/vite-plugin-svelte": "^2.0.3",
    "svelte": "^3.55.1",
    "svelte-preprocess": "^5.0.1",
    "vite": "^4.1.4"
  }
}
